README.md
setup.py
ltck/__init__.py
ltck.egg-info/PKG-INFO
ltck.egg-info/SOURCES.txt
ltck.egg-info/dependency_links.txt
ltck.egg-info/requires.txt
ltck.egg-info/top_level.txt